tbvaccine.pth
tbvaccine/__init__.py
tbvaccine/__main__.py
tbvaccine/cli.py
tbvaccine/tbv.py
tbvaccine/tests.py
tbvaccine/version.py
tbvaccine-0.3.1.dist-info/METADATA
tbvaccine-0.3.1.dist-info/RECORD
tbvaccine-0.3.1.dist-info/WHEEL
tbvaccine-0.3.1.dist-info/entry_points.txt
tbvaccine-0.3.1.dist-info/top_level.txt
