Metadata-Version: 2.1
Name: tbvaccine
Version: 0.3.1
Summary: A utility that cures the horrible traceback displays in Python, making them more readable.
Home-page: https://github.com/skorokithakis/tbvaccine/
Author: Stavros Korokithakis
Author-email: hi@stavros.io
License: MIT
Platform: UNKNOWN
Classifier: License :: OSI Approved :: MIT License
Classifier: Programming Language :: Python
Classifier: Programming Language :: Python :: 2.5
Classifier: Programming Language :: Python :: 2.6
Classifier: Programming Language :: Python :: 2.7
Classifier: Programming Language :: Python :: 3.2
Classifier: Programming Language :: Python :: 3.3
Classifier: Programming Language :: Python :: 3.4
Classifier: Programming Language :: Python :: 3.5
Classifier: Programming Language :: Python :: 3.6
Classifier: Topic :: Software Development :: Libraries :: Python Modules
Requires-Dist: pygments
